dstl/__init__.py
dstl/types.py
dstl/cli/__init__.py
dstl/cli/translate.py
dstl/prodigy/__init__.py
dstl/prodigy/recipes.py
dstl/translate/__init__.py
dstl/translate/azure.py
dstl/translate/base.py
dstl/translate/core.py
dstl/translate/google.py
dstl/translate/registry.py
dstl/translate/transformers.py
dstl-0.0.2.dist-info/entry_points.txt
dstl-0.0.2.dist-info/LICENSE
dstl-0.0.2.dist-info/WHEEL
dstl-0.0.2.dist-info/METADATA
dstl-0.0.2.dist-info/RECORD
