Metadata-Version: 2.1
Name: dstl
Version: 0.0.2
Summary: DataSet TransLation (DSTL) provides utilities to translate annotated natural language data from one language to another.
Home-page: https://github.com/kabirkhan/dstl
License: UNKNOWN
Author: Kabir Khan
Author-email: kabirkhan1137@outlook.com
Requires-Python: >=3.6
Classifier: Intended Audience :: Information Technology
Classifier: Intended Audience :: System Administrators
Classifier: Operating System :: OS Independent
Classifier: Programming Language :: Python :: 3
Classifier: Programming Language :: Python
Classifier: Topic :: Software Development :: Libraries :: Application Frameworks
Classifier: Topic :: Software Development :: Libraries :: Python Modules
Classifier: Topic :: Software Development :: Libraries
Classifier: Topic :: Software Development
Classifier: Typing :: Typed
Classifier: Development Status :: 4 - Beta
Classifier: Intended Audience :: Developers
Classifier: Programming Language :: Python :: 3 :: Only
Classifier: Programming Language :: Python :: 3.6
Classifier: Programming Language :: Python :: 3.7
Classifier: Programming Language :: Python :: 3.8
Classifier: License :: OSI Approved :: MIT License
Requires-Dist: httpx >=0.14,<1.0
Requires-Dist: pydantic >=1.5,<1.6
Requires-Dist: spacy >=2.3,<2.4
Requires-Dist: torch >=1.6.0,<1.7.0
Requires-Dist: transformers >=3.0.0,<3.1.0
Requires-Dist: typer >=0.3.1,<1.0
Requires-Dist: colorama ; extra == "all"
Requires-Dist: click-completion ; extra == "all"
Requires-Dist: jupyterlab >= 1.2.0, <1.3 ; extra == "dev"
Requires-Dist: ipywidgets ; extra == "dev"
Requires-Dist: autoflake >=1.3.1,<2.0.0 ; extra == "dev"
Requires-Dist: flake8 >=3.8.3,<4.0.0 ; extra == "dev"
Requires-Dist: mkdocs >=1.1.2,<2.0.0 ; extra == "doc"
Requires-Dist: mkdocs-material >=5.4.0,<6.0.0 ; extra == "doc"
Requires-Dist: markdown-include >=0.5.1,<0.6.0 ; extra == "doc"
Requires-Dist: mkdocstrings ; extra == "doc"
Requires-Dist: pytest == 5.3.0 ; extra == "test"
Requires-Dist: pytest-cov ; extra == "test"
Requires-Dist: coverage ; extra == "test"
Requires-Dist: pytest-xdist ; extra == "test"
Requires-Dist: pytest-sugar ; extra == "test"
Requires-Dist: mypy ; extra == "test"
Requires-Dist: black ; extra == "test"
Requires-Dist: isort ; extra == "test"
Provides-Extra: all
Provides-Extra: dev
Provides-Extra: doc
Provides-Extra: test
